{
  "language": [
    "Bharat Sharma built Meta-Brain AGI",
    "built Meta-Brain AGI with 6",
    "AGI with 6 modules. Parliament",
    "6 modules. Parliament AGI has",
    "Parliament AGI has 6 senators",
    "has 6 senators with selective",
    "senators with selective memory. Paper:",
    "selective memory. Paper: Imagination as",
    "Bharat Sharma is building Parliament",
    "is building Parliament AGI at",
    "Parliament AGI at PhenexAI Research",
    "at PhenexAI Research in May",
    "Research in May 2026. The",
    "May 2026. The Meta-Brain has",
    "The Meta-Brain has six modules:",
    "has six modules: world model,",
    "modules: world model, simulation checker,",
    "model, simulation checker, universe memory",
    "checker, universe memory box, decision",
    "memory box, decision engine, theory",
    "decision engine, theory generator, and",
    "theory generator, and imagination engine.",
    "and imagination engine. Parliament AGI",
    "engine. Parliament AGI is not",
    "AGI is not a chatbot.",
    "not a chatbot. It is",
    "chatbot. It is a distributed",
    "is a distributed intelligence with",
    "distributed intelligence with persistent memory.",
    "with persistent memory. Each senator",
    "memory. Each senator specializes in",
    "senator specializes in a domain",
    "in a domain and votes",
    "domain and votes on questions",
    "votes on questions brought before",
    "questions brought before Parliament. The",
    "before Parliament. The paper is",
    "The paper is called Imagination",
    "is called Imagination as Infrastructure:",
    "Imagination as Infrastructure: a new",
    "Infrastructure: a new theory of",
    "new theory of AGI. Memory",
    "of AGI. Memory that compounds",
    "Memory that compounds is fundamentally",
    "compounds is fundamentally different from",
    "fundamentally different from memory that",
    "from memory that retrieves. The",
    "that retrieves. The goal is",
    "The goal is not to",
    "is not to pass a",
    "to pass a Turing test",
    "a Turing test but to",
    "test but to generate genuinely",
    "to generate genuinely new theories.",
    "genuinely new theories. Building AGI",
    "theories. Building AGI requires not",
    "AGI requires not just intelligence",
    "not just intelligence but wisdom,",
    "intelligence but wisdom, which requires",
    "wisdom, which requires memory across"
  ],
  "reading": [
    {
      "source": "bharat_identity",
      "text": "Bharat Sharma built Meta-Brain AGI with 6 modules. Parliament AGI has 6 senators with selective memory. Paper: Imagination as Infrastructure.",
      "time": "2026-05-14T08:27:54.926119"
    },
    {
      "source": "phenexai_deep",
      "text": "\nBharat Sharma is building Parliament AGI at PhenexAI Research in May 2026.\nThe Meta-Brain has six modules: world model, simulation checker, universe memory box, decision engine, theory generator, and imagination engine.\nParliament AGI is not a chatbot. It is a distributed intelligence with persiste",
      "time": "2026-05-14T11:36:48.796491"
    }
  ]
}